spring_config/__init__.py
spring_config/client.py
spring_config/utils.py
spring_config_client-0.2.dist-info/LICENSE
spring_config_client-0.2.dist-info/METADATA
spring_config_client-0.2.dist-info/WHEEL
spring_config_client-0.2.dist-info/top_level.txt
spring_config_client-0.2.dist-info/RECORD
