Metadata-Version: 2.1
Name: spring-config-client
Version: 0.2
Summary: A client for Spring Config Server
Home-page: https://realbucksavage.github.io/spring-config-client
Author: realbucksavage
License: MIT
Project-URL: Documentation, https://github.com/realbucksavage/spring-config-client
Project-URL: Code, https://github.com/realbucksavage/spring-config-client
Project-URL: Issue tracker, https://github.com/realbucksavage/spring-config-client/issues
Platform: UNKNOWN
Classifier: Programming Language :: Python :: 3.6
Classifier: Programming Language :: Python :: 3.7
Classifier: Development Status :: 4 - Beta
Classifier: Intended Audience :: Developers
Classifier: License :: OSI Approved :: MIT License
Classifier: Operating System :: OS Independent
Classifier: Topic :: Software Development :: Libraries :: Java Libraries
Requires-Python: >=3.6.0
Requires-Dist: requests (>=2.22.0)
